mudskipper/__init__.py
mudskipper/client.py
mudskipper/connection.py
mudskipper/endpoint.py
mudskipper/response.py
mudskipper/timekeeper.py
mudskipper-1.2.dist-info/METADATA
mudskipper-1.2.dist-info/RECORD
mudskipper-1.2.dist-info/WHEEL
mudskipper-1.2.dist-info/top_level.txt
